{
  "default_helmet": {
    "name": "L Met",
    "type": "helmet",
    "item": "magma_cream",
    "custom_model_data": 8794,
    "enchanted": false,
    "description": "Achetable",
    "level": "2",
    "stats": {
      "vitality": [
        2,
        0
      ],
      "mind": [
        1,
        0
      ],
      "strength": [
        2,
        0
      ],
      "intelligence": [
        2,
        0
      ],
      "chance": [
        2,
        0
      ],
      "agility": [
        2,
        0
      ]
    }
  },
  "Sword": {
    "name": "Useless Sword",
    "type": "sword",
    "item": "magma_cream",
    "custom_model_data": 36999,
    "enchanted": false,
    "description": "Achetable",
    "level": "2",
    "stats": {
      "vitality": [
        0,
        0
      ],
      "mind": [
        0,
        0
      ],
      "strength": [
        2,
        0
      ],
      "intelligence": [
        0,
        0
      ],
      "chance": [
        2,
        0
      ],
      "agility": [
        1,
        0
      ]
    },
    "critical": [
      1,
      25
    ],
    "damage": [
      1,
      2
    ]
  },
  "Chestplate": {
    "name": "Cheh Splate",
    "type": "chestplate",
    "item": "leather_chestplate",
    "custom_model_data": 5966,
    "enchanted": false,
    "description": "Achetable",
    "level": "2",
    "stats": {
      "vitality": [
        5,
        0
      ],
      "mind": [
        3,
        0
      ],
      "strength": [
        2,
        0
      ],
      "intelligence": [
        2,
        0
      ],
      "chance": [
        2,
        0
      ],
      "agility": [
        2,
        0
      ]
    }
  },
  "Legging": {
    "name": "Jam Bière",
    "type": "leggings",
    "item": "leather_leggings",
    "custom_model_data": 96479,
    "enchanted": false,
    "description": "Achetable",
    "level": "2",
    "stats": {
      "vitality": [
        3,
        0
      ],
      "mind": [
        2,
        0
      ],
      "strength": [
        2,
        0
      ],
      "intelligence": [
        2,
        0
      ],
      "chance": [
        2,
        0
      ],
      "agility": [
        2,
        0
      ]
    }
  },
  "Boots": {
    "name": "Sans Dalle",
    "type": "boots",
    "item": "leather_boots",
    "custom_model_data": 16870,
    "enchanted": false,
    "description": "Achetable",
    "level": "2",
    "stats": {
      "vitality": [
        3,
        0
      ],
      "mind": [
        1,
        0
      ],
      "strength": [
        2,
        0
      ],
      "intelligence": [
        2,
        0
      ],
      "chance": [
        2,
        0
      ],
      "agility": [
        2,
        0
      ]
    }
  },
  "Necklace": {
    "name": "Nek Laisse",
    "type": "necklace",
    "item": "magma_cream",
    "custom_model_data": 4032,
    "enchanted": false,
    "description": "Achetable",
    "level": "2",
    "stats": {
      "vitality": [
        4,
        0
      ],
      "mind": [
        3,
        0
      ],
      "strength": [
        1,
        0
      ],
      "intelligence": [
        1,
        0
      ],
      "chance": [
        1,
        0
      ],
      "agility": [
        1,
        0
      ]
    }
  },
  "Ring": {
    "name": "Nigr",
    "type": "ring",
    "item": "magma_cream",
    "custom_model_data": 37069,
    "enchanted": false,
    "description": "Achetable",
    "level": "2",
    "stats": {
      "vitality": [
        2,
        0
      ],
      "mind": [
        1,
        0
      ],
      "strength": [
        2,
        0
      ],
      "intelligence": [
        2,
        0
      ],
      "chance": [
        2,
        0
      ],
      "agility": [
        2,
        0
      ]
    }
  },
  "Belt": {
    "name": "Sceat's Slip",
    "type": "belt",
    "item": "magma_cream",
    "custom_model_data": 68780,
    "enchanted": false,
    "description": "Achetable",
    "level": "2",
    "stats": {
      "vitality": [
        2,
        0
      ],
      "mind": [
        2,
        0
      ],
      "strength": [
        2,
        0
      ],
      "intelligence": [
        2,
        0
      ],
      "chance": [
        2,
        0
      ],
      "agility": [
        2,
        0
      ]
    }
  },
  "Stick": {
    "name": "Useless Stick",
    "type": "stick",
    "item": "magma_cream",
    "custom_model_data": 25673,
    "enchanted": false,
    "description": "Achetable",
    "level": "2",
    "stats": {
      "vitality": [
        0,
        0
      ],
      "mind": [
        0,
        0
      ],
      "strength": [
        0,
        0
      ],
      "intelligence": [
        2,
        0
      ],
      "chance": [
        2,
        0
      ],
      "agility": [
        0,
        0
      ]
    },
    "critical": [
      1,
      20
    ],
    "damage": [
      1,
      3
    ]
  },
  "Bow": {
    "name": "Useless Bow",
    "type": "bow",
    "item": "magma_cream",
    "custom_model_data": 40896,
    "enchanted": false,
    "description": "Achetable",
    "level": "2",
    "stats": {
      "vitality": [
        0,
        0
      ],
      "mind": [
        0,
        0
      ],
      "strength": [
        0,
        0
      ],
      "intelligence": [
        0,
        0
      ],
      "chance": [
        1,
        0
      ],
      "agility": [
        3,
        0
      ]
    },
    "critical": [
      1,
      20
    ],
    "damage": [
      1,
      3
    ]
  },
  "Axe": {
    "name": "Useless Axe",
    "type": "axe",
    "item": "magma_cream",
    "custom_model_data": 48762,
    "enchanted": false,
    "description": "Achetable",
    "level": "2",
    "stats": {
      "vitality": [
        0,
        0
      ],
      "mind": [
        0,
        0
      ],
      "strength": [
        3,
        0
      ],
      "intelligence": [
        0,
        0
      ],
      "chance": [
        1,
        0
      ],
      "agility": [
        1,
        0
      ]
    },
    "critical": [
      1,
      25
    ],
    "damage": [
      1,
      3
    ]
  }
}